brickdetector/__init__.py
brickdetector/detector.py
brickdetector-0.1.0.dist-info/licenses/LICENSE
brickdetector-0.1.0.dist-info/METADATA
brickdetector-0.1.0.dist-info/WHEEL
brickdetector-0.1.0.dist-info/top_level.txt
brickdetector-0.1.0.dist-info/RECORD
