Metadata-Version: 2.4
Name: brickdetector
Version: 0.1.0
Summary: A package for detecting the word 'brick' in any form within any provided text
Author-email: Kaper365 <kacperdezor@kaper365.de>
License-Expression: MIT
Project-URL: Source, https://github.com/kaper365/brickdetector
Classifier: Programming Language :: Python :: 3
Classifier: Operating System :: OS Independent
Requires-Python: >=3.9
License-File: LICENSE
Dynamic: license-file
